Metadata-Version: 2.1
Name: developers-chamber
Version: 0.1.35
Summary: A small plugin which help with development, deployment, git
Home-page: https://github.com/druids/django-project-info
Author: Druids team
Author-email: matllubos@gmail.com
License: MIT
Keywords: django,skripts,easy live,git,bitbucket,Jira
Provides-Extra: slack
Provides-Extra: aws
Provides-Extra: qa
Provides-Extra: bitbucket
Provides-Extra: gitlab
Provides-Extra: jira
Provides-Extra: toggle
Provides-Extra: git
License-File: LICENSE
